chaturbate_poller/__init__.py
chaturbate_poller/__main__.py
chaturbate_poller/constants.py
chaturbate_poller/exceptions.py
chaturbate_poller/py.typed
chaturbate_poller/cli/__init__.py
chaturbate_poller/cli/commands.py
chaturbate_poller/config/__init__.py
chaturbate_poller/config/backoff.py
chaturbate_poller/config/manager.py
chaturbate_poller/core/__init__.py
chaturbate_poller/core/client.py
chaturbate_poller/core/polling.py
chaturbate_poller/core/runner.py
chaturbate_poller/database/__init__.py
chaturbate_poller/database/influxdb_handler.py
chaturbate_poller/database/nested_types.py
chaturbate_poller/handlers/__init__.py
chaturbate_poller/handlers/database_handler.py
chaturbate_poller/handlers/event_handler.py
chaturbate_poller/handlers/factory.py
chaturbate_poller/handlers/logging_handler.py
chaturbate_poller/logging/__init__.py
chaturbate_poller/logging/config.py
chaturbate_poller/logging/exception_hook.py
chaturbate_poller/models/__init__.py
chaturbate_poller/models/api_response.py
chaturbate_poller/models/event.py
chaturbate_poller/models/event_data.py
chaturbate_poller/models/media.py
chaturbate_poller/models/message.py
chaturbate_poller/models/options.py
chaturbate_poller/models/tip.py
chaturbate_poller/models/user.py
chaturbate_poller/utils/__init__.py
chaturbate_poller/utils/error_handler.py
chaturbate_poller/utils/format_messages.py
chaturbate_poller/utils/helpers.py
chaturbate_poller-5.1.8.dist-info/METADATA
chaturbate_poller-5.1.8.dist-info/WHEEL
chaturbate_poller-5.1.8.dist-info/entry_points.txt
chaturbate_poller-5.1.8.dist-info/licenses/LICENSE
chaturbate_poller-5.1.8.dist-info/RECORD
