Metadata-Version: 2.4
Name: chaturbate-poller
Version: 5.1.8
Summary: Python library for interacting with the Chaturbate Events API
Project-URL: changelog, https://github.com/MountainGod2/chaturbate_poller/blob/main/CHANGELOG.md
Project-URL: documentation, https://mountaingod2.github.io/chaturbate_poller/
Project-URL: homepage, https://github.com/MountainGod2/chaturbate_poller
Project-URL: issues, https://github.com/MountainGod2/chaturbate_poller/issues
Project-URL: repository, https://github.com/MountainGod2/chaturbate_poller
Author-email: MountainGod2 <admin@reid.ca>
License-Expression: MIT
License-File: LICENSE
Keywords: api,chaturbate,poller,python
Classifier: Development Status :: 5 - Production/Stable
Classifier: Intended Audience :: Developers
Classifier: License :: OSI Approved :: MIT License
Classifier: Operating System :: OS Independent
Classifier: Programming Language :: Python :: 3 :: Only
Classifier: Programming Language :: Python :: 3.12
Classifier: Programming Language :: Python :: 3.13
Classifier: Topic :: Software Development :: Libraries :: Python Modules
Classifier: Typing :: Typed
Requires-Python: >=3.12
Requires-Dist: backoff==2.2.1
Requires-Dist: httpx==0.28.1
Requires-Dist: pydantic==2.11.7
Requires-Dist: python-dotenv==1.1.1
Requires-Dist: rich-click==1.8.9
Requires-Dist: rich==14.1.0
